sepia/__init__.py
sepia/processor.py
sepia/template.py
sepia/variable.py
sepia/__pycache__/__init__.cpython-36.pyc
sepia/__pycache__/processor.cpython-36.pyc
sepia/__pycache__/template.cpython-36.pyc
sepia/__pycache__/variable.cpython-36.pyc
sepia-0.7.809.data/scripts/sepia-cli
sepia-0.7.809.dist-info/METADATA
sepia-0.7.809.dist-info/RECORD
sepia-0.7.809.dist-info/WHEEL
sepia-0.7.809.dist-info/top_level.txt
